[
    {
        "Exp": 1200,
        "PlaceUnlock": 1,
        "Preview": "全新科研任務，更多聯動機師的戰鬥序列，更多科技素材",
        "ID": 1,
        "Name": null
    },
    {
        "Exp": 1200,
        "PlaceUnlock": 2,
        "Preview": "全新科研任務，更多聯動機師的戰鬥序列，更多科技素材",
        "ID": 2,
        "Name": null
    },
    {
        "Exp": 1200,
        "PlaceUnlock": 3,
        "Preview": "全新科研任務，更多聯動機師的戰鬥序列，更多科技素材",
        "ID": 3,
        "Name": null
    },
    {
        "Exp": 1200,
        "PlaceUnlock": 0,
        "Preview": "全新科研任務，更多聯動機師的戰鬥序列，更多科技素材",
        "ID": 4,
        "Name": null
    },
    {
        "Exp": 1200,
        "PlaceUnlock": 4,
        "Preview": "全新科研任務，更多聯動機師的戰鬥序列，更多科技素材",
        "ID": 5,
        "Name": null
    },
    {
        "Exp": 1200,
        "PlaceUnlock": 0,
        "Preview": "全新科研任務，更多聯動機師的戰鬥序列，更多科技素材",
        "ID": 6,
        "Name": null
    },
    {
        "Exp": 1200,
        "PlaceUnlock": 5,
        "Preview": "全新科研任務，更多聯動機師的戰鬥序列，更多科技素材",
        "ID": 7,
        "Name": null
    },
    {
        "Exp": 1200,
        "PlaceUnlock": 0,
        "Preview": "全新科研任務，更多聯動機師的戰鬥序列，更多科技素材",
        "ID": 8,
        "Name": null
    },
    {
        "Exp": 1200,
        "PlaceUnlock": 0,
        "Preview": "全新科研任務，更多聯動機師的戰鬥序列，更多科技素材",
        "ID": 9,
        "Name": null
    },
    {
        "Exp": 1200,
        "PlaceUnlock": 0,
        "Preview": "全新科研任務，更多聯動機師的戰鬥序列，更多科技素材",
        "ID": 10,
        "Name": null
    },
    {
        "Exp": 1200,
        "PlaceUnlock": 0,
        "Preview": "全新科研任務，更多聯動機師的戰鬥序列，更多科技素材",
        "ID": 11,
        "Name": null
    },
    {
        "Exp": 1200,
        "PlaceUnlock": 0,
        "Preview": "全新科研任務，更多聯動機師的戰鬥序列，更多科技素材",
        "ID": 12,
        "Name": null
    },
    {
        "Exp": 1200,
        "PlaceUnlock": 0,
        "Preview": "全新科研任務，更多聯動機師的戰鬥序列，更多科技素材",
        "ID": 13,
        "Name": null
    },
    {
        "Exp": 1200,
        "PlaceUnlock": 0,
        "Preview": "全新科研任務，更多聯動機師的戰鬥序列，更多科技素材",
        "ID": 14,
        "Name": null
    },
    {
        "Exp": 1200,
        "PlaceUnlock": 0,
        "Preview": "全新科研任務，更多聯動機師的戰鬥序列，更多科技素材",
        "ID": 15,
        "Name": null
    },
    {
        "Exp": 1200,
        "PlaceUnlock": 0,
        "Preview": "全新科研任務，更多聯動機師的戰鬥序列，更多科技素材",
        "ID": 16,
        "Name": null
    },
    {
        "Exp": 1200,
        "PlaceUnlock": 0,
        "Preview": "全新科研任務，更多聯動機師的戰鬥序列，更多科技素材",
        "ID": 17,
        "Name": null
    },
    {
        "Exp": 1200,
        "PlaceUnlock": 0,
        "Preview": "全新科研任務，更多聯動機師的戰鬥序列，更多科技素材",
        "ID": 18,
        "Name": null
    },
    {
        "Exp": 1200,
        "PlaceUnlock": 0,
        "Preview": "全新科研任務，更多聯動機師的戰鬥序列，更多科技素材",
        "ID": 19,
        "Name": null
    },
    {
        "Exp": 1200,
        "PlaceUnlock": 0,
        "Preview": "全新科研任務，更多聯動機師的戰鬥序列，更多科技素材",
        "ID": 20,
        "Name": null
    },
    {
        "Exp": 1200,
        "PlaceUnlock": 0,
        "Preview": "全新科研任務，更多聯動機師的戰鬥序列，更多科技素材",
        "ID": 21,
        "Name": null
    },
    {
        "Exp": 1200,
        "PlaceUnlock": 0,
        "Preview": "全新科研任務，更多聯動機師的戰鬥序列，更多科技素材",
        "ID": 22,
        "Name": null
    },
    {
        "Exp": 1200,
        "PlaceUnlock": 0,
        "Preview": "全新科研任務，更多聯動機師的戰鬥序列，更多科技素材",
        "ID": 23,
        "Name": null
    },
    {
        "Exp": 1200,
        "PlaceUnlock": 0,
        "Preview": "全新科研任務，更多聯動機師的戰鬥序列，更多科技素材",
        "ID": 24,
        "Name": null
    },
    {
        "Exp": 1200,
        "PlaceUnlock": 0,
        "Preview": "全新科研任務，更多聯動機師的戰鬥序列，更多科技素材",
        "ID": 25,
        "Name": null
    },
    {
        "Exp": 1200,
        "PlaceUnlock": 0,
        "Preview": "全新科研任務，更多聯動機師的戰鬥序列，更多科技素材",
        "ID": 26,
        "Name": null
    },
    {
        "Exp": 1200,
        "PlaceUnlock": 0,
        "Preview": "全新科研任務，更多聯動機師的戰鬥序列，更多科技素材",
        "ID": 27,
        "Name": null
    },
    {
        "Exp": 1200,
        "PlaceUnlock": 0,
        "Preview": "全新科研任務，更多聯動機師的戰鬥序列，更多科技素材",
        "ID": 28,
        "Name": null
    },
    {
        "Exp": 1200,
        "PlaceUnlock": 0,
        "Preview": "全新科研任務，更多聯動機師的戰鬥序列，更多科技素材",
        "ID": 29,
        "Name": null
    },
    {
        "Exp": 1200,
        "PlaceUnlock": 0,
        "Preview": "全新科研任務，更多聯動機師的戰鬥序列，更多科技素材",
        "ID": 30,
        "Name": null
    },
    {
        "Exp": 1200,
        "PlaceUnlock": 0,
        "Preview": "全新科研任務，更多聯動機師的戰鬥序列，更多科技素材",
        "ID": 31,
        "Name": null
    },
    {
        "Exp": 1200,
        "PlaceUnlock": 0,
        "Preview": "全新科研任務，更多聯動機師的戰鬥序列，更多科技素材",
        "ID": 32,
        "Name": null
    },
    {
        "Exp": 1200,
        "PlaceUnlock": 0,
        "Preview": "全新科研任務，更多聯動機師的戰鬥序列，更多科技素材",
        "ID": 33,
        "Name": null
    },
    {
        "Exp": 1200,
        "PlaceUnlock": 0,
        "Preview": "全新科研任務，更多聯動機師的戰鬥序列，更多科技素材",
        "ID": 34,
        "Name": null
    },
    {
        "Exp": 1200,
        "PlaceUnlock": 0,
        "Preview": "全新科研任務，更多聯動機師的戰鬥序列，更多科技素材",
        "ID": 35,
        "Name": null
    },
    {
        "Exp": 1200,
        "PlaceUnlock": 0,
        "Preview": "全新科研任務，更多聯動機師的戰鬥序列，更多科技素材",
        "ID": 36,
        "Name": null
    },
    {
        "Exp": 1200,
        "PlaceUnlock": 0,
        "Preview": "全新科研任務，更多聯動機師的戰鬥序列，更多科技素材",
        "ID": 37,
        "Name": null
    },
    {
        "Exp": 1200,
        "PlaceUnlock": 0,
        "Preview": "全新科研任務，更多聯動機師的戰鬥序列，更多科技素材",
        "ID": 38,
        "Name": null
    },
    {
        "Exp": 1200,
        "PlaceUnlock": 0,
        "Preview": "全新科研任務，更多聯動機師的戰鬥序列，更多科技素材",
        "ID": 39,
        "Name": null
    },
    {
        "Exp": 1200,
        "PlaceUnlock": 0,
        "Preview": "全新科研任務，更多聯動機師的戰鬥序列，更多科技素材",
        "ID": 40,
        "Name": null
    }
]